ab_addnm/addnm.py
ab_addnm-0.2.dist-info/METADATA
ab_addnm-0.2.dist-info/RECORD
ab_addnm-0.2.dist-info/WHEEL
ab_addnm-0.2.dist-info/top_level.txt
