Metadata-Version: 2.1
Name: ab-addnm
Version: 0.2
Summary: A simple function for mathematical operations
Home-page: UNKNOWN
Author: Abir Hassan
Author-email: u1804110@student.cuet.ac.bd
License: MIT
Platform: UNKNOWN
Classifier: Programming Language :: Python :: 3
Classifier: License :: OSI Approved :: MIT License
Classifier: Operating System :: OS Independent
